[{"type":"source","location":"src\\Core\\Form\\AbstractFormType.php","range":[{"line":56,"character":0},{"line":56,"character":0}],"enabled":true},{"type":"source","location":"src\\Core\\List\\AbstractListType.php","range":[{"line":217,"character":0},{"line":217,"character":0}],"enabled":true},{"type":"source","location":"src\\Core\\Form\\Renderer\\BootstrapFormRenderer.php","range":[{"line":311,"character":0},{"line":311,"character":0}],"enabled":true},{"type":"source","location":"src\\Core\\Services\\ClosureFormatterService.php","range":[{"line":22,"character":0},{"line":22,"character":0}],"enabled":true},{"type":"source","location":"bin\\console.php","range":[{"line":114,"character":0},{"line":114,"character":0}],"enabled":true},{"type":"source","location":"bin\\console.php","range":[{"line":116,"character":0},{"line":116,"character":0}],"enabled":true},{"type":"source","location":"bin\\console.php","range":[{"line":141,"character":0},{"line":141,"character":0}],"enabled":true},{"type":"source","location":"bin\\console.php","range":[{"line":296,"character":0},{"line":296,"character":0}],"enabled":true},{"type":"source","location":"bin\\console.php","range":[{"line":344,"character":0},{"line":344,"character":0}],"enabled":true},{"type":"source","location":"src\\Core\\Form\\DataSanitizer.php","range":[{"line":16,"character":0},{"line":16,"character":0}],"enabled":true},{"type":"source","location":"src\\Core\\Formatters\\EmailFormatter.php","range":[{"line":22,"character":0},{"line":22,"character":0}],"enabled":true},{"type":"source","location":"src\\Core\\Formatters\\EmailFormatter.php","range":[{"line":36,"character":0},{"line":36,"character":0}],"enabled":true},{"type":"source","location":"src\\Core\\Services\\FormatterService.php","range":[{"line":69,"character":0},{"line":69,"character":0}],"enabled":true},{"type":"source","location":"src\\Core\\Services\\FormatterService.php","range":[{"line":78,"character":0},{"line":78,"character":0}],"enabled":true},{"type":"source","location":"src\\Core\\Services\\FormatterService.php","range":[{"line":95,"character":0},{"line":95,"character":0}],"enabled":true},{"type":"source","location":"src\\Core\\Services\\FormatterService.php","range":[{"line":112,"character":0},{"line":112,"character":0}],"enabled":true},{"type":"source","location":"src\\Core\\Services\\FormatterService.php","range":[{"line":141,"character":0},{"line":141,"character":0}],"enabled":true},{"type":"source","location":"src\\Core\\Services\\FormatterService.php","range":[{"line":143,"character":0},{"line":143,"character":0}],"enabled":true},{"type":"source","location":"src\\Core\\Form\\FormHandler.php","range":[{"line":217,"character":0},{"line":217,"character":0}],"enabled":true},{"type":"source","location":"src\\Core\\Form\\Validation\\Rules\\NumberValidator.php","range":[{"line":188,"character":0},{"line":188,"character":0}],"enabled":true},{"type":"source","location":"src\\Core\\Form\\Validation\\Rules\\NumberValidator.php","range":[{"line":224,"character":0},{"line":224,"character":0}],"enabled":true},{"type":"source","location":"src\\Core\\Formatters\\PhoneNumberFormatter.php","range":[{"line":76,"character":0},{"line":76,"character":0}],"enabled":true},{"type":"source","location":"src\\Config\\list_fields\\testy_edit.php","range":[{"line":175,"character":0},{"line":175,"character":0}],"enabled":true},{"type":"source","location":"src\\Core\\Formatters\\TextFormatter.php","range":[{"line":22,"character":0},{"line":22,"character":0}],"enabled":true},{"type":"source","location":"src\\Core\\Formatters\\TextFormatter.php","range":[{"line":79,"character":0},{"line":79,"character":0}],"enabled":true},{"type":"source","location":"src\\Core\\Form\\Validation\\Rules\\TextValidator.php","range":[{"line":17,"character":0},{"line":17,"character":0}],"enabled":true},{"type":"source","location":"src\\Core\\Form\\Validation\\Validator.php","range":[{"line":198,"character":0},{"line":198,"character":0}],"enabled":true},{"type":"source","location":"src\\Core\\Form\\Validation\\Validator.php","range":[{"line":213,"character":0},{"line":213,"character":0}],"enabled":true},{"type":"source","location":"src\\Core\\Form\\Validation\\Validator.php","range":[{"line":255,"character":0},{"line":255,"character":0}],"enabled":true},{"type":"source","location":"src\\Core\\Form\\Validation\\Validator.php","range":[{"line":270,"character":0},{"line":270,"character":0}],"enabled":true}]